[
    {
        "experience_points":0,
        "level":1,
        "proficiency_bonus":2
    },
    {
        "experience_points":300,
        "level":2,
        "proficiency_bonus":2
    },
    {
        "experience_points":900,
        "level":3,
        "proficiency_bonus":2
    },
    {
        "experience_points":2700,
        "level":4,
        "proficiency_bonus":2
    },
    {
        "experience_points":6500,
        "level":5,
        "proficiency_bonus":3
    },
    {
        "experience_points":14000,
        "level":6,
        "proficiency_bonus":3
    },
    {
        "experience_points":23000,
        "level":7,
        "proficiency_bonus":3
    },
    {
        "experience_points":34000,
        "level":8,
        "proficiency_bonus":3
    },
    {
        "experience_points":48000,
        "level":9,
        "proficiency_bonus":4
    },
    {
        "experience_points":64000,
        "level":10,
        "proficiency_bonus":4
    },
    {
        "experience_points":85000,
        "level":11,
        "proficiency_bonus":4
    },
    {
        "experience_points":100000,
        "level":12,
        "proficiency_bonus":4
    },
    {
        "experience_points":120000,
        "level":13,
        "proficiency_bonus":5
    },
    {
        "experience_points":140000,
        "level":14,
        "proficiency_bonus":5
    },
    {
        "experience_points":165000,
        "level":15,
        "proficiency_bonus":5
    },
    {
        "experience_points":195000,
        "level":16,
        "proficiency_bonus":5
    },
    {
        "experience_points":225000,
        "level":17,
        "proficiency_bonus":6
    },
    {
        "experience_points":265000,
        "level":18,
        "proficiency_bonus":6
    },
    {
        "experience_points":305000,
        "level":19,
        "proficiency_bonus":6
    },
    {
        "experience_points":355000,
        "level":20,
        "proficiency_bonus":6
    },
    {
        "experience_points":409727,
        "level":21,
        "proficiency_bonus":6
    },
    {
        "experience_points":473422,
        "level":22,
        "proficiency_bonus":6
    },
    {
        "experience_points":546473,
        "level":23,
        "proficiency_bonus":6
    },
    {
        "experience_points":630115,
        "level":24,
        "proficiency_bonus":6
    },
    {
        "experience_points":725673,
        "level":25,
        "proficiency_bonus":6
    },
    {
        "experience_points":834564,
        "level":26,
        "proficiency_bonus":6
    },
    {
        "experience_points":958296,
        "level":27,
        "proficiency_bonus":6
    },
    {
        "experience_points":1098466,
        "level":28,
        "proficiency_bonus":6
    },
    {
        "experience_points":1256763,
        "level":29,
        "proficiency_bonus":6
    },
    {
        "experience_points":1434968,
        "level":30,
        "proficiency_bonus":6
    },
    {
        "experience_points":1634950,
        "level":31,
        "proficiency_bonus":6
    },
    {
        "experience_points":1858671,
        "level":32,
        "proficiency_bonus":6
    },
    {
        "experience_points":2108183,
        "level":33,
        "proficiency_bonus":6
    },
    {
        "experience_points":2385628,
        "level":34,
        "proficiency_bonus":6
    },
    {
        "experience_points":2693241,
        "level":35,
        "proficiency_bonus":6
    },
    {
        "experience_points":3033345,
        "level":36,
        "proficiency_bonus":6
    },
    {
        "experience_points":3408356,
        "level":37,
        "proficiency_bonus":6
    },
    {
        "experience_points":3820780,
        "level":38,
        "proficiency_bonus":6
    },
    {
        "experience_points":4273213,
        "level":39,
        "proficiency_bonus":6
    },
    {
        "experience_points":4768343,
        "level":40,
        "proficiency_bonus":6
    }
]